smartbot-0.1.dist-info/WHEEL
smartbot-0.1.dist-info/metadata.json
smartbot-0.1.dist-info/top_level.txt
smartbot-0.1.dist-info/DESCRIPTION.rst
smartbot-0.1.dist-info/dependency_links.txt
smartbot-0.1.dist-info/RECORD
smartbot-0.1.dist-info/METADATA
smartbot/nasa_behaviour.py
smartbot/evi_behaviour.py
smartbot/google_image_behaviour.py
smartbot/bot.py
smartbot/wolfram_behaviour.py
smartbot/behaviour.py
smartbot/basic_behaviour.py
smartbot/utils.py
smartbot/talk_behaviour.py
smartbot/joke_behaviour.py
smartbot/external_api.py
smartbot/bing_image_behaviour.py
smartbot/slack_bot.py
smartbot/telegram_bot.py
smartbot/__init__.py
smartbot/friendly_behaviour.py
smartbot/behaviour_control.py
smartbot/loader_behaviour.py
smartbot/translate_behaviour.py
smartbot-0.1.data/scripts/smartbot.py
