Metadata-Version: 2.0
Name: smartbot
Version: 0.1
Summary: The most smart bot in telegram and slack
Home-page: http://github.com/pedrohml/smartbot
Author: Pedro Lira
Author-email: pedrohml@gmail.com
License: MIT
Keywords: python telegram slack bot smart api
Platform: UNKNOWN
Classifier: Development Status :: 5 - Production/Stable
Classifier: Intended Audience :: Developers
Classifier: Operating System :: OS Independent
Classifier: Topic :: Software Development :: Libraries :: Python Modules
Classifier: Topic :: Communications :: Chat
Classifier: Topic :: Internet
Classifier: Programming Language :: Python
Classifier: Programming Language :: Python :: 2
Classifier: Programming Language :: Python :: 2.6
Classifier: Programming Language :: Python :: 2.7
Classifier: Programming Language :: Python :: 3
Classifier: Programming Language :: Python :: 3.2
Classifier: Programming Language :: Python :: 3.3
Classifier: Programming Language :: Python :: 3.4
Requires-Dist: funcsigs (==0.4)
Requires-Dist: future (==0.15.2)
Requires-Dist: lxml (==3.5.0)
Requires-Dist: mock (==1.3.0)
Requires-Dist: pbr (==1.8.1)
Requires-Dist: requests (==2.8.1)
Requires-Dist: six (==1.10.0)
Requires-Dist: wheel (==0.24.0)
